analogs_finder/__init__.py
analogs_finder/main.py
analogs_finder/helpers/__init__.py
analogs_finder/helpers/formats.py
analogs_finder/helpers/helpers.py
analogs_finder/rank_methods/__init__.py
analogs_finder/rank_methods/phase.py
analogs_finder/search_methods/__init__.py
analogs_finder/search_methods/fingerprints.py
analogs_finder/search_methods/methods.py
tests/__init__.py
tests/test_fingerprints.py
tests/test_helpers.py
tests/test_methods.py
tests/test_phase.py
analogs_finder-1.0.0.dist-info/LICENSE
analogs_finder-1.0.0.dist-info/METADATA
analogs_finder-1.0.0.dist-info/WHEEL
analogs_finder-1.0.0.dist-info/top_level.txt
analogs_finder-1.0.0.dist-info/RECORD
